{
  "facility": "8am-ai",
  "version": "0.1.0",
  "counts": {
    "transcripts": 18,
    "normalized": 17,
    "summary_only": 4,
    "ideas": 170,
    "themes": 13,
    "directives": 50,
    "published": 0,
    "drafted": 7,
    "queued": 46,
    "backlog": 119
  },
  "last_run": "2026-06-25T14:39:54Z",
  "carry_forward": [
    "IDEA-0094",
    "IDEA-0057",
    "IDEA-0080",
    "IDEA-0100",
    "IDEA-0096",
    "IDEA-0112",
    "IDEA-0074",
    "IDEA-0091",
    "IDEA-0093",
    "IDEA-0070",
    "IDEA-0095",
    "IDEA-0071",
    "IDEA-0072",
    "IDEA-0117",
    "IDEA-0034",
    "IDEA-0101",
    "IDEA-0043",
    "IDEA-0032",
    "IDEA-0089",
    "IDEA-0035",
    "IDEA-0014",
    "IDEA-0029",
    "IDEA-0020",
    "IDEA-0081",
    "IDEA-0015",
    "IDEA-0108",
    "IDEA-0098",
    "IDEA-0118",
    "IDEA-0099",
    "IDEA-0107",
    "IDEA-0102",
    "IDEA-0051",
    "IDEA-0115",
    "IDEA-0111",
    "IDEA-0104",
    "IDEA-0062",
    "IDEA-0090",
    "IDEA-0085",
    "IDEA-0088",
    "IDEA-0109",
    "IDEA-0106",
    "IDEA-0018",
    "IDEA-0119",
    "IDEA-0038",
    "IDEA-0105",
    "IDEA-0110"
  ],
  "cursors": {
    "gdrive": {
      "last_modified": "2026-06-24T16:20:48.095Z"
    },
    "intake": {
      "last_processed_meeting": "2026-06-24"
    }
  },
  "backlog": [
    "IDEA-0042",
    "IDEA-0086",
    "IDEA-0016",
    "IDEA-0097",
    "IDEA-0066",
    "IDEA-0087",
    "IDEA-0113",
    "IDEA-0116",
    "IDEA-0040",
    "IDEA-0077",
    "IDEA-0075",
    "IDEA-0053",
    "IDEA-0063",
    "IDEA-0082",
    "IDEA-0049",
    "IDEA-0004",
    "IDEA-0037",
    "IDEA-0023",
    "IDEA-0052",
    "IDEA-0031",
    "IDEA-0114",
    "IDEA-0033",
    "IDEA-0024",
    "IDEA-0068",
    "IDEA-0022",
    "IDEA-0036",
    "IDEA-0079",
    "IDEA-0003",
    "IDEA-0041",
    "IDEA-0007",
    "IDEA-0065",
    "IDEA-0012",
    "IDEA-0019",
    "IDEA-0059",
    "IDEA-0021",
    "IDEA-0076",
    "IDEA-0054",
    "IDEA-0067",
    "IDEA-0011",
    "IDEA-0030",
    "IDEA-0055",
    "IDEA-0069",
    "IDEA-0028",
    "IDEA-0006",
    "IDEA-0008",
    "IDEA-0039",
    "IDEA-0010",
    "IDEA-0046",
    "IDEA-0001",
    "IDEA-0060",
    "IDEA-0048",
    "IDEA-0047",
    "IDEA-0045",
    "IDEA-0050",
    "IDEA-0017",
    "IDEA-0025",
    "IDEA-0009",
    "IDEA-0027",
    "IDEA-0005",
    "IDEA-0002",
    "IDEA-0044",
    "IDEA-0056",
    "IDEA-0084",
    "IDEA-0058",
    "IDEA-0092",
    "IDEA-0122",
    "IDEA-0013",
    "IDEA-0026",
    "IDEA-0064",
    "IDEA-0121",
    "IDEA-0151",
    "IDEA-0061",
    "IDEA-0128",
    "IDEA-0136",
    "IDEA-0168",
    "IDEA-0123",
    "IDEA-0167",
    "IDEA-0154",
    "IDEA-0142",
    "IDEA-0127",
    "IDEA-0146",
    "IDEA-0126",
    "IDEA-0161",
    "IDEA-0135",
    "IDEA-0143",
    "IDEA-0125",
    "IDEA-0162",
    "IDEA-0134",
    "IDEA-0137",
    "IDEA-0145",
    "IDEA-0159",
    "IDEA-0141",
    "IDEA-0152",
    "IDEA-0157",
    "IDEA-0163",
    "IDEA-0170",
    "IDEA-0139",
    "IDEA-0124",
    "IDEA-0140",
    "IDEA-0160",
    "IDEA-0130",
    "IDEA-0129",
    "IDEA-0156",
    "IDEA-0144",
    "IDEA-0147",
    "IDEA-0155",
    "IDEA-0164",
    "IDEA-0149",
    "IDEA-0150",
    "IDEA-0148",
    "IDEA-0131",
    "IDEA-0169",
    "IDEA-0133",
    "IDEA-0165",
    "IDEA-0138",
    "IDEA-0153",
    "IDEA-0132",
    "IDEA-0166",
    "IDEA-0158"
  ]
}